kamonohashi/__init__.py
kamonohashi/op/__init__.py
kamonohashi/op/object_storage.py
kamonohashi/op/rest/__init__.py
kamonohashi/op/rest/api_client.py
kamonohashi/op/rest/configuration.py
kamonohashi/op/rest/rest.py
kamonohashi/op/rest/api/__init__.py
kamonohashi/op/rest/api/account_api.py
kamonohashi/op/rest/api/data_api.py
kamonohashi/op/rest/api/data_set_api.py
kamonohashi/op/rest/api/inference_api.py
kamonohashi/op/rest/api/notebook_api.py
kamonohashi/op/rest/api/preprocessing_api.py
kamonohashi/op/rest/api/storage_api.py
kamonohashi/op/rest/api/tenant_api.py
kamonohashi/op/rest/api/training_api.py
kamonohashi/op/rest/models/__init__.py
kamonohashi/op/rest/models/account_api_models_account_output_model.py
kamonohashi/op/rest/models/account_api_models_login_input_model.py
kamonohashi/op/rest/models/account_api_models_login_output_model.py
kamonohashi/op/rest/models/account_api_models_switch_tenant_input_model.py
kamonohashi/op/rest/models/components_add_file_input_model.py
kamonohashi/op/rest/models/components_container_image_input_model.py
kamonohashi/op/rest/models/components_container_image_output_model.py
kamonohashi/op/rest/models/components_git_commit_input_model.py
kamonohashi/op/rest/models/components_git_commit_nullable_input_model.py
kamonohashi/op/rest/models/components_git_commit_output_model.py
kamonohashi/op/rest/models/data_api_models_add_files_input_model.py
kamonohashi/op/rest/models/data_api_models_create_input_model.py
kamonohashi/op/rest/models/data_api_models_data_file_output_model.py
kamonohashi/op/rest/models/data_api_models_data_files_output_model.py
kamonohashi/op/rest/models/data_api_models_details_output_model.py
kamonohashi/op/rest/models/data_api_models_edit_input_model.py
kamonohashi/op/rest/models/data_api_models_index_output_model.py
kamonohashi/op/rest/models/data_api_models_preprocess_history_output_model.py
kamonohashi/op/rest/models/data_set_api_models_create_input_model.py
kamonohashi_sdk-4.0.2.dist-info/DESCRIPTION.rst
kamonohashi_sdk-4.0.2.dist-info/METADATA
kamonohashi_sdk-4.0.2.dist-info/RECORD
kamonohashi_sdk-4.0.2.dist-info/WHEEL
kamonohashi_sdk-4.0.2.dist-info/metadata.json
kamonohashi_sdk-4.0.2.dist-info/top_level.txt
