Metadata-Version: 2.0
Name: kamonohashi-sdk
Version: 4.0.2
Summary: KAMONOHASHI SDK
Home-page: https://github.com/KAMONOHASHI/kamonohashi
Author: NS Solutions Corporation
Author-email: kamonohashi-support@jp.nssol.nipponsteel.com
License: Apache License 2.0
Platform: UNKNOWN
Requires-Dist: certifi (>=2017.4.17)
Requires-Dist: six (>=1.10)
Requires-Dist: urllib3 (>=1.23)
